{
  "openapi": "3.0.1",
  "info": {
    "title": "ItAssets",
    "version": "1.0"
  },
  "paths": {
    "/api/Auth/register": {
      "post": {
        "tags": [
          "Auth"
        ],
        "requestBody": {
          "content": {
            "application/json": {
              "schema": {
                "$ref": "#/components/schemas/RegisterUserDto"
              }
            },
            "text/json": {
              "schema": {
                "$ref": "#/components/schemas/RegisterUserDto"
              }
            },
            "application/*+json": {
              "schema": {
                "$ref": "#/components/schemas/RegisterUserDto"
              }
            }
          }
        },
        "responses": {
          "200": {
            "description": "OK"
          }
        }
      }
    },
    "/api/Auth/confirmemail": {
      "get": {
        "tags": [
          "Auth"
        ],
        "parameters": [
          {
            "name": "userId",
            "in": "query",
            "schema": {
              "type": "string"
            }
          },
          {
            "name": "token",
            "in": "query",
            "schema": {
              "type": "string"
            }
          }
        ],
        "responses": {
          "200": {
            "description": "OK"
          }
        }
      }
    },
    "/api/Auth/login": {
      "post": {
        "tags": [
          "Auth"
        ],
        "requestBody": {
          "content": {
            "application/json": {
              "schema": {
                "$ref": "#/components/schemas/LoginDto"
              }
            },
            "text/json": {
              "schema": {
                "$ref": "#/components/schemas/LoginDto"
              }
            },
            "application/*+json": {
              "schema": {
                "$ref": "#/components/schemas/LoginDto"
              }
            }
          }
        },
        "responses": {
          "200": {
            "description": "OK"
          }
        }
      }
    },
    "/api/Brand/GetAll": {
      "get": {
        "tags": [
          "Brand"
        ],
        "responses": {
          "200": {
            "description": "OK"
          }
        }
      }
    },
    "/api/Brand/GetbyId/{id}": {
      "get": {
        "tags": [
          "Brand"
        ],
        "parameters": [
          {
            "name": "id",
            "in": "path",
            "required": true,
            "schema": {
              "type": "string",
              "format": "uuid"
            }
          }
        ],
        "responses": {
          "200": {
            "description": "OK"
          }
        }
      }
    },
    "/api/Brand/PostBrand": {
      "post": {
        "tags": [
          "Brand"
        ],
        "requestBody": {
          "content": {
            "application/json": {
              "schema": {
                "$ref": "#/components/schemas/BrandDTO"
              }
            },
            "text/json": {
              "schema": {
                "$ref": "#/components/schemas/BrandDTO"
              }
            },
            "application/*+json": {
              "schema": {
                "$ref": "#/components/schemas/BrandDTO"
              }
            }
          }
        },
        "responses": {
          "200": {
            "description": "OK"
          }
        }
      }
    },
    "/api/Brand/PutBrand/{id}": {
      "put": {
        "tags": [
          "Brand"
        ],
        "parameters": [
          {
            "name": "id",
            "in": "path",
            "required": true,
            "schema": {
              "type": "string",
              "format": "uuid"
            }
          }
        ],
        "requestBody": {
          "content": {
            "application/json": {
              "schema": {
                "$ref": "#/components/schemas/BrandDTO"
              }
            },
            "text/json": {
              "schema": {
                "$ref": "#/components/schemas/BrandDTO"
              }
            },
            "application/*+json": {
              "schema": {
                "$ref": "#/components/schemas/BrandDTO"
              }
            }
          }
        },
        "responses": {
          "200": {
            "description": "OK"
          }
        }
      }
    },
    "/api/Brand/Delete/{id}": {
      "delete": {
        "tags": [
          "Brand"
        ],
        "parameters": [
          {
            "name": "id",
            "in": "path",
            "required": true,
            "schema": {
              "type": "string",
              "format": "uuid"
            }
          }
        ],
        "responses": {
          "200": {
            "description": "OK"
          }
        }
      }
    },
    "/api/Category/GetAll": {
      "get": {
        "tags": [
          "Category"
        ],
        "responses": {
          "200": {
            "description": "OK"
          }
        }
      }
    },
    "/api/Category/GetbyId/{id}": {
      "get": {
        "tags": [
          "Category"
        ],
        "parameters": [
          {
            "name": "id",
            "in": "path",
            "required": true,
            "schema": {
              "type": "string",
              "format": "uuid"
            }
          }
        ],
        "responses": {
          "200": {
            "description": "OK"
          }
        }
      }
    },
    "/api/Category/PostCategory": {
      "post": {
        "tags": [
          "Category"
        ],
        "requestBody": {
          "content": {
            "application/json": {
              "schema": {
                "$ref": "#/components/schemas/CategoryDTO"
              }
            },
            "text/json": {
              "schema": {
                "$ref": "#/components/schemas/CategoryDTO"
              }
            },
            "application/*+json": {
              "schema": {
                "$ref": "#/components/schemas/CategoryDTO"
              }
            }
          }
        },
        "responses": {
          "200": {
            "description": "OK"
          }
        }
      }
    },
    "/api/Category/PutCategory/{id}": {
      "put": {
        "tags": [
          "Category"
        ],
        "parameters": [
          {
            "name": "id",
            "in": "path",
            "required": true,
            "schema": {
              "type": "string",
              "format": "uuid"
            }
          }
        ],
        "requestBody": {
          "content": {
            "application/json": {
              "schema": {
                "$ref": "#/components/schemas/CategoryDTO"
              }
            },
            "text/json": {
              "schema": {
                "$ref": "#/components/schemas/CategoryDTO"
              }
            },
            "application/*+json": {
              "schema": {
                "$ref": "#/components/schemas/CategoryDTO"
              }
            }
          }
        },
        "responses": {
          "200": {
            "description": "OK"
          }
        }
      }
    },
    "/api/Category/Delete/{id}": {
      "delete": {
        "tags": [
          "Category"
        ],
        "parameters": [
          {
            "name": "id",
            "in": "path",
            "required": true,
            "schema": {
              "type": "string",
              "format": "uuid"
            }
          }
        ],
        "responses": {
          "200": {
            "description": "OK"
          }
        }
      }
    },
    "/api/Device/GetAllDevices": {
      "get": {
        "tags": [
          "Device"
        ],
        "responses": {
          "200": {
            "description": "OK"
          }
        }
      }
    },
    "/api/Device/{id}": {
      "get": {
        "tags": [
          "Device"
        ],
        "parameters": [
          {
            "name": "id",
            "in": "path",
            "required": true,
            "schema": {
              "type": "string",
              "format": "uuid"
            }
          }
        ],
        "responses": {
          "200": {
            "description": "OK"
          }
        }
      }
    },
    "/api/Device/create-with-photo": {
      "post": {
        "tags": [
          "Device"
        ],
        "requestBody": {
          "content": {
            "multipart/form-data": {
              "schema": {
                "type": "object",
                "properties": {
                  "Name": {
                    "type": "string"
                  },
                  "SerialNumber": {
                    "type": "string"
                  },
                  "Photo": {
                    "type": "string",
                    "format": "binary"
                  },
                  "Status": {
                    "type": "string"
                  },
                  "BrandId": {
                    "type": "string",
                    "format": "uuid"
                  },
                  "CategoryID": {
                    "type": "string",
                    "format": "uuid"
                  },
                  "SupplierID": {
                    "type": "string",
                    "format": "uuid"
                  },
                  "IsFaulty": {
                    "type": "boolean"
                  },
                  "IsAvailable": {
                    "type": "boolean"
                  },
                  "Qty": {
                    "type": "integer",
                    "format": "int32"
                  }
                }
              },
              "encoding": {
                "Name": {
                  "style": "form"
                },
                "SerialNumber": {
                  "style": "form"
                },
                "Photo": {
                  "style": "form"
                },
                "Status": {
                  "style": "form"
                },
                "BrandId": {
                  "style": "form"
                },
                "CategoryID": {
                  "style": "form"
                },
                "SupplierID": {
                  "style": "form"
                },
                "IsFaulty": {
                  "style": "form"
                },
                "IsAvailable": {
                  "style": "form"
                },
                "Qty": {
                  "style": "form"
                }
              }
            }
          }
        },
        "responses": {
          "200": {
            "description": "OK"
          }
        }
      }
    },
    "/api/Device/{id}/update-with-photo": {
      "put": {
        "tags": [
          "Device"
        ],
        "parameters": [
          {
            "name": "id",
            "in": "path",
            "required": true,
            "schema": {
              "type": "string",
              "format": "uuid"
            }
          }
        ],
        "requestBody": {
          "content": {
            "multipart/form-data": {
              "schema": {
                "type": "object",
                "properties": {
                  "Name": {
                    "type": "string"
                  },
                  "SerialNumber": {
                    "type": "string"
                  },
                  "Status": {
                    "type": "string"
                  },
                  "BrandId": {
                    "type": "string",
                    "format": "uuid"
                  },
                  "CategoryID": {
                    "type": "string",
                    "format": "uuid"
                  },
                  "SupplierID": {
                    "type": "string",
                    "format": "uuid"
                  },
                  "IsFaulty": {
                    "type": "boolean"
                  },
                  "IsAvailable": {
                    "type": "boolean"
                  },
                  "Photo": {
                    "type": "string",
                    "format": "binary"
                  },
                  "Qty": {
                    "type": "integer",
                    "format": "int32"
                  }
                }
              },
              "encoding": {
                "Name": {
                  "style": "form"
                },
                "SerialNumber": {
                  "style": "form"
                },
                "Status": {
                  "style": "form"
                },
                "BrandId": {
                  "style": "form"
                },
                "CategoryID": {
                  "style": "form"
                },
                "SupplierID": {
                  "style": "form"
                },
                "IsFaulty": {
                  "style": "form"
                },
                "IsAvailable": {
                  "style": "form"
                },
                "Photo": {
                  "style": "form"
                },
                "Qty": {
                  "style": "form"
                }
              }
            }
          }
        },
        "responses": {
          "200": {
            "description": "OK"
          }
        }
      }
    },
    "/api/Device/{id}/delete-with-photo": {
      "delete": {
        "tags": [
          "Device"
        ],
        "parameters": [
          {
            "name": "id",
            "in": "path",
            "required": true,
            "schema": {
              "type": "string",
              "format": "uuid"
            }
          }
        ],
        "responses": {
          "200": {
            "description": "OK"
          }
        }
      }
    },
    "/api/DeviceMaintainanceSchedule/GetAll": {
      "get": {
        "tags": [
          "DeviceMaintainanceSchedule"
        ],
        "responses": {
          "200": {
            "description": "OK"
          }
        }
      }
    },
    "/api/DeviceMaintainanceSchedule/GetbyId/{id}": {
      "get": {
        "tags": [
          "DeviceMaintainanceSchedule"
        ],
        "parameters": [
          {
            "name": "id",
            "in": "path",
            "required": true,
            "schema": {
              "type": "string",
              "format": "uuid"
            }
          }
        ],
        "responses": {
          "200": {
            "description": "OK"
          }
        }
      }
    },
    "/api/DeviceMaintainanceSchedule/PostMaintainance": {
      "post": {
        "tags": [
          "DeviceMaintainanceSchedule"
        ],
        "requestBody": {
          "content": {
            "application/json": {
              "schema": {
                "$ref": "#/components/schemas/DeviceMaintainanceScheduleDTO"
              }
            },
            "text/json": {
              "schema": {
                "$ref": "#/components/schemas/DeviceMaintainanceScheduleDTO"
              }
            },
            "application/*+json": {
              "schema": {
                "$ref": "#/components/schemas/DeviceMaintainanceScheduleDTO"
              }
            }
          }
        },
        "responses": {
          "200": {
            "description": "OK"
          }
        }
      }
    },
    "/api/DeviceMaintainanceSchedule/PutSchedule/{id}": {
      "put": {
        "tags": [
          "DeviceMaintainanceSchedule"
        ],
        "parameters": [
          {
            "name": "id",
            "in": "path",
            "required": true,
            "schema": {
              "type": "string",
              "format": "uuid"
            }
          }
        ],
        "requestBody": {
          "content": {
            "application/json": {
              "schema": {
                "$ref": "#/components/schemas/DeviceMaintainanceScheduleDTO"
              }
            },
            "text/json": {
              "schema": {
                "$ref": "#/components/schemas/DeviceMaintainanceScheduleDTO"
              }
            },
            "application/*+json": {
              "schema": {
                "$ref": "#/components/schemas/DeviceMaintainanceScheduleDTO"
              }
            }
          }
        },
        "responses": {
          "200": {
            "description": "OK"
          }
        }
      }
    },
    "/api/DeviceMaintainanceSchedule/Delete/{id}": {
      "delete": {
        "tags": [
          "DeviceMaintainanceSchedule"
        ],
        "parameters": [
          {
            "name": "id",
            "in": "path",
            "required": true,
            "schema": {
              "type": "string",
              "format": "uuid"
            }
          }
        ],
        "responses": {
          "200": {
            "description": "OK"
          }
        }
      }
    },
    "/api/DeviceRequests/GetAll": {
      "get": {
        "tags": [
          "DeviceRequests"
        ],
        "responses": {
          "200": {
            "description": "OK"
          }
        }
      }
    },
    "/api/DeviceRequests/GetbyId/{id}": {
      "get": {
        "tags": [
          "DeviceRequests"
        ],
        "parameters": [
          {
            "name": "id",
            "in": "path",
            "required": true,
            "schema": {
              "type": "string",
              "format": "uuid"
            }
          }
        ],
        "responses": {
          "200": {
            "description": "OK"
          }
        }
      }
    },
    "/api/DeviceRequests/PostDeviceRequest": {
      "post": {
        "tags": [
          "DeviceRequests"
        ],
        "requestBody": {
          "content": {
            "application/json": {
              "schema": {
                "$ref": "#/components/schemas/DeviceRequestsDTO"
              }
            },
            "text/json": {
              "schema": {
                "$ref": "#/components/schemas/DeviceRequestsDTO"
              }
            },
            "application/*+json": {
              "schema": {
                "$ref": "#/components/schemas/DeviceRequestsDTO"
              }
            }
          }
        },
        "responses": {
          "200": {
            "description": "OK"
          }
        }
      }
    },
    "/api/DeviceRequests/PutDeviceRequest/{id}": {
      "put": {
        "tags": [
          "DeviceRequests"
        ],
        "parameters": [
          {
            "name": "id",
            "in": "path",
            "required": true,
            "schema": {
              "type": "string",
              "format": "uuid"
            }
          }
        ],
        "requestBody": {
          "content": {
            "application/json": {
              "schema": {
                "$ref": "#/components/schemas/DeviceRequestsDTO"
              }
            },
            "text/json": {
              "schema": {
                "$ref": "#/components/schemas/DeviceRequestsDTO"
              }
            },
            "application/*+json": {
              "schema": {
                "$ref": "#/components/schemas/DeviceRequestsDTO"
              }
            }
          }
        },
        "responses": {
          "200": {
            "description": "OK"
          }
        }
      }
    },
    "/api/DeviceRequests/Delete/{id}": {
      "delete": {
        "tags": [
          "DeviceRequests"
        ],
        "parameters": [
          {
            "name": "id",
            "in": "path",
            "required": true,
            "schema": {
              "type": "string",
              "format": "uuid"
            }
          }
        ],
        "responses": {
          "200": {
            "description": "OK"
          }
        }
      }
    },
    "/api/DeviceTransfer/GetAll": {
      "get": {
        "tags": [
          "DeviceTransfer"
        ],
        "responses": {
          "200": {
            "description": "OK"
          }
        }
      }
    },
    "/api/DeviceTransfer/GetbyId/{id}": {
      "get": {
        "tags": [
          "DeviceTransfer"
        ],
        "parameters": [
          {
            "name": "id",
            "in": "path",
            "required": true,
            "schema": {
              "type": "string",
              "format": "uuid"
            }
          }
        ],
        "responses": {
          "200": {
            "description": "OK"
          }
        }
      }
    },
    "/api/DeviceTransfer/PostDeviceTransfer": {
      "post": {
        "tags": [
          "DeviceTransfer"
        ],
        "requestBody": {
          "content": {
            "application/json": {
              "schema": {
                "$ref": "#/components/schemas/DeviceTransferDTO"
              }
            },
            "text/json": {
              "schema": {
                "$ref": "#/components/schemas/DeviceTransferDTO"
              }
            },
            "application/*+json": {
              "schema": {
                "$ref": "#/components/schemas/DeviceTransferDTO"
              }
            }
          }
        },
        "responses": {
          "200": {
            "description": "OK"
          }
        }
      }
    },
    "/api/DeviceTransfer/PutDeviceTransfer/{id}": {
      "put": {
        "tags": [
          "DeviceTransfer"
        ],
        "parameters": [
          {
            "name": "id",
            "in": "path",
            "required": true,
            "schema": {
              "type": "string",
              "format": "uuid"
            }
          }
        ],
        "requestBody": {
          "content": {
            "application/json": {
              "schema": {
                "$ref": "#/components/schemas/DeviceTransferDTO"
              }
            },
            "text/json": {
              "schema": {
                "$ref": "#/components/schemas/DeviceTransferDTO"
              }
            },
            "application/*+json": {
              "schema": {
                "$ref": "#/components/schemas/DeviceTransferDTO"
              }
            }
          }
        },
        "responses": {
          "200": {
            "description": "OK"
          }
        }
      }
    },
    "/api/DeviceTransfer/Delete/{id}": {
      "delete": {
        "tags": [
          "DeviceTransfer"
        ],
        "parameters": [
          {
            "name": "id",
            "in": "path",
            "required": true,
            "schema": {
              "type": "string",
              "format": "uuid"
            }
          }
        ],
        "responses": {
          "200": {
            "description": "OK"
          }
        }
      }
    },
    "/api/Employee/GetAll": {
      "get": {
        "tags": [
          "Employee"
        ],
        "responses": {
          "200": {
            "description": "OK"
          }
        }
      }
    },
    "/api/Employee/GetbyId/{id}": {
      "get": {
        "tags": [
          "Employee"
        ],
        "parameters": [
          {
            "name": "id",
            "in": "path",
            "required": true,
            "schema": {
              "type": "string",
              "format": "uuid"
            }
          }
        ],
        "responses": {
          "200": {
            "description": "OK"
          }
        }
      }
    },
    "/api/Employee/PostEmployee": {
      "post": {
        "tags": [
          "Employee"
        ],
        "requestBody": {
          "content": {
            "application/json": {
              "schema": {
                "$ref": "#/components/schemas/EmployeeDTO"
              }
            },
            "text/json": {
              "schema": {
                "$ref": "#/components/schemas/EmployeeDTO"
              }
            },
            "application/*+json": {
              "schema": {
                "$ref": "#/components/schemas/EmployeeDTO"
              }
            }
          }
        },
        "responses": {
          "200": {
            "description": "OK"
          }
        }
      }
    },
    "/api/Employee/PutEmployee/{id}": {
      "put": {
        "tags": [
          "Employee"
        ],
        "parameters": [
          {
            "name": "id",
            "in": "path",
            "required": true,
            "schema": {
              "type": "string",
              "format": "uuid"
            }
          }
        ],
        "requestBody": {
          "content": {
            "application/json": {
              "schema": {
                "$ref": "#/components/schemas/EmployeeDTO"
              }
            },
            "text/json": {
              "schema": {
                "$ref": "#/components/schemas/EmployeeDTO"
              }
            },
            "application/*+json": {
              "schema": {
                "$ref": "#/components/schemas/EmployeeDTO"
              }
            }
          }
        },
        "responses": {
          "200": {
            "description": "OK"
          }
        }
      }
    },
    "/api/Employee/Delete/{id}": {
      "delete": {
        "tags": [
          "Employee"
        ],
        "parameters": [
          {
            "name": "id",
            "in": "path",
            "required": true,
            "schema": {
              "type": "string",
              "format": "uuid"
            }
          }
        ],
        "responses": {
          "200": {
            "description": "OK"
          }
        }
      }
    },
    "/api/EmployeeDeviceAssign/GetAll": {
      "get": {
        "tags": [
          "EmployeeDeviceAssign"
        ],
        "responses": {
          "200": {
            "description": "OK"
          }
        }
      }
    },
    "/api/EmployeeDeviceAssign/GetbyId/{id}": {
      "get": {
        "tags": [
          "EmployeeDeviceAssign"
        ],
        "parameters": [
          {
            "name": "id",
            "in": "path",
            "required": true,
            "schema": {
              "type": "string",
              "format": "uuid"
            }
          }
        ],
        "responses": {
          "200": {
            "description": "OK"
          }
        }
      }
    },
    "/api/EmployeeDeviceAssign/Delete/{id}": {
      "delete": {
        "tags": [
          "EmployeeDeviceAssign"
        ],
        "parameters": [
          {
            "name": "id",
            "in": "path",
            "required": true,
            "schema": {
              "type": "string",
              "format": "uuid"
            }
          }
        ],
        "responses": {
          "200": {
            "description": "OK"
          }
        }
      }
    },
    "/api/EmployeeDeviceAssign/EmpDeviceAssignment": {
      "post": {
        "tags": [
          "EmployeeDeviceAssign"
        ],
        "requestBody": {
          "content": {
            "application/json": {
              "schema": {
                "$ref": "#/components/schemas/EmployeeDeviceAssignmentDTO"
              }
            },
            "text/json": {
              "schema": {
                "$ref": "#/components/schemas/EmployeeDeviceAssignmentDTO"
              }
            },
            "application/*+json": {
              "schema": {
                "$ref": "#/components/schemas/EmployeeDeviceAssignmentDTO"
              }
            }
          }
        },
        "responses": {
          "200": {
            "description": "OK"
          }
        }
      }
    },
    "/api/EmployeeDeviceAssign/ReturnDevice": {
      "put": {
        "tags": [
          "EmployeeDeviceAssign"
        ],
        "requestBody": {
          "content": {
            "application/json": {
              "schema": {
                "$ref": "#/components/schemas/EmployeeDeviceReturn"
              }
            },
            "text/json": {
              "schema": {
                "$ref": "#/components/schemas/EmployeeDeviceReturn"
              }
            },
            "application/*+json": {
              "schema": {
                "$ref": "#/components/schemas/EmployeeDeviceReturn"
              }
            }
          }
        },
        "responses": {
          "200": {
            "description": "OK"
          }
        }
      }
    },
    "/api/Office/GetAll": {
      "get": {
        "tags": [
          "Office"
        ],
        "responses": {
          "200": {
            "description": "OK"
          }
        }
      }
    },
    "/api/Office/GetbyId/{id}": {
      "get": {
        "tags": [
          "Office"
        ],
        "parameters": [
          {
            "name": "id",
            "in": "path",
            "required": true,
            "schema": {
              "type": "string",
              "format": "uuid"
            }
          }
        ],
        "responses": {
          "200": {
            "description": "OK"
          }
        }
      }
    },
    "/api/Office/PostOffice": {
      "post": {
        "tags": [
          "Office"
        ],
        "requestBody": {
          "content": {
            "application/json": {
              "schema": {
                "$ref": "#/components/schemas/OfficeDTO"
              }
            },
            "text/json": {
              "schema": {
                "$ref": "#/components/schemas/OfficeDTO"
              }
            },
            "application/*+json": {
              "schema": {
                "$ref": "#/components/schemas/OfficeDTO"
              }
            }
          }
        },
        "responses": {
          "200": {
            "description": "OK"
          }
        }
      }
    },
    "/api/Office/PutOffice/{id}": {
      "put": {
        "tags": [
          "Office"
        ],
        "parameters": [
          {
            "name": "id",
            "in": "path",
            "required": true,
            "schema": {
              "type": "string",
              "format": "uuid"
            }
          }
        ],
        "requestBody": {
          "content": {
            "application/json": {
              "schema": {
                "$ref": "#/components/schemas/OfficeDTO"
              }
            },
            "text/json": {
              "schema": {
                "$ref": "#/components/schemas/OfficeDTO"
              }
            },
            "application/*+json": {
              "schema": {
                "$ref": "#/components/schemas/OfficeDTO"
              }
            }
          }
        },
        "responses": {
          "200": {
            "description": "OK"
          }
        }
      }
    },
    "/api/Office/Delete/{id}": {
      "delete": {
        "tags": [
          "Office"
        ],
        "parameters": [
          {
            "name": "id",
            "in": "path",
            "required": true,
            "schema": {
              "type": "string",
              "format": "uuid"
            }
          }
        ],
        "responses": {
          "200": {
            "description": "OK"
          }
        }
      }
    },
    "/api/OfficeDeviceAssign/GetAll": {
      "get": {
        "tags": [
          "OfficeDeviceAssign"
        ],
        "responses": {
          "200": {
            "description": "OK"
          }
        }
      }
    },
    "/api/OfficeDeviceAssign/GetbyId/{id}": {
      "get": {
        "tags": [
          "OfficeDeviceAssign"
        ],
        "parameters": [
          {
            "name": "id",
            "in": "path",
            "required": true,
            "schema": {
              "type": "string",
              "format": "uuid"
            }
          }
        ],
        "responses": {
          "200": {
            "description": "OK"
          }
        }
      }
    },
    "/api/OfficeDeviceAssign/Delete/{id}": {
      "delete": {
        "tags": [
          "OfficeDeviceAssign"
        ],
        "parameters": [
          {
            "name": "id",
            "in": "path",
            "required": true,
            "schema": {
              "type": "string",
              "format": "uuid"
            }
          }
        ],
        "responses": {
          "200": {
            "description": "OK"
          }
        }
      }
    },
    "/api/OfficeDeviceAssign/OffDeviceAssignment": {
      "post": {
        "tags": [
          "OfficeDeviceAssign"
        ],
        "requestBody": {
          "content": {
            "application/json": {
              "schema": {
                "$ref": "#/components/schemas/OfficeDeviceAssignmentDTO"
              }
            },
            "text/json": {
              "schema": {
                "$ref": "#/components/schemas/OfficeDeviceAssignmentDTO"
              }
            },
            "application/*+json": {
              "schema": {
                "$ref": "#/components/schemas/OfficeDeviceAssignmentDTO"
              }
            }
          }
        },
        "responses": {
          "200": {
            "description": "OK"
          }
        }
      }
    },
    "/api/OfficeDeviceAssign/ReturnDevice": {
      "put": {
        "tags": [
          "OfficeDeviceAssign"
        ],
        "requestBody": {
          "content": {
            "application/json": {
              "schema": {
                "$ref": "#/components/schemas/OfficeDeviceReturnDTO"
              }
            },
            "text/json": {
              "schema": {
                "$ref": "#/components/schemas/OfficeDeviceReturnDTO"
              }
            },
            "application/*+json": {
              "schema": {
                "$ref": "#/components/schemas/OfficeDeviceReturnDTO"
              }
            }
          }
        },
        "responses": {
          "200": {
            "description": "OK"
          }
        }
      }
    },
    "/api/Supplier/GetAll": {
      "get": {
        "tags": [
          "Supplier"
        ],
        "responses": {
          "200": {
            "description": "OK"
          }
        }
      }
    },
    "/api/Supplier/GetbyId/{id}": {
      "get": {
        "tags": [
          "Supplier"
        ],
        "parameters": [
          {
            "name": "id",
            "in": "path",
            "required": true,
            "schema": {
              "type": "string",
              "format": "uuid"
            }
          }
        ],
        "responses": {
          "200": {
            "description": "OK"
          }
        }
      }
    },
    "/api/Supplier/PostSupplier": {
      "post": {
        "tags": [
          "Supplier"
        ],
        "requestBody": {
          "content": {
            "application/json": {
              "schema": {
                "$ref": "#/components/schemas/SupplierDTO"
              }
            },
            "text/json": {
              "schema": {
                "$ref": "#/components/schemas/SupplierDTO"
              }
            },
            "application/*+json": {
              "schema": {
                "$ref": "#/components/schemas/SupplierDTO"
              }
            }
          }
        },
        "responses": {
          "200": {
            "description": "OK"
          }
        }
      }
    },
    "/api/Supplier/PutSupplier/{id}": {
      "put": {
        "tags": [
          "Supplier"
        ],
        "parameters": [
          {
            "name": "id",
            "in": "path",
            "required": true,
            "schema": {
              "type": "string",
              "format": "uuid"
            }
          }
        ],
        "requestBody": {
          "content": {
            "application/json": {
              "schema": {
                "$ref": "#/components/schemas/SupplierDTO"
              }
            },
            "text/json": {
              "schema": {
                "$ref": "#/components/schemas/SupplierDTO"
              }
            },
            "application/*+json": {
              "schema": {
                "$ref": "#/components/schemas/SupplierDTO"
              }
            }
          }
        },
        "responses": {
          "200": {
            "description": "OK"
          }
        }
      }
    },
    "/api/Supplier/Delete/{id}": {
      "delete": {
        "tags": [
          "Supplier"
        ],
        "parameters": [
          {
            "name": "id",
            "in": "path",
            "required": true,
            "schema": {
              "type": "string",
              "format": "uuid"
            }
          }
        ],
        "responses": {
          "200": {
            "description": "OK"
          }
        }
      }
    }
  },
  "components": {
    "schemas": {
      "BrandDTO": {
        "type": "object",
        "properties": {
          "id": {
            "type": "string",
            "format": "uuid"
          },
          "name": {
            "type": "string",
            "nullable": true
          }
        },
        "additionalProperties": false
      },
      "CategoryDTO": {
        "type": "object",
        "properties": {
          "id": {
            "type": "string",
            "format": "uuid"
          },
          "name": {
            "type": "string",
            "nullable": true
          }
        },
        "additionalProperties": false
      },
      "DeviceMaintainanceScheduleDTO": {
        "type": "object",
        "properties": {
          "deviceID": {
            "type": "string",
            "format": "uuid"
          },
          "description": {
            "type": "string",
            "nullable": true
          },
          "date": {
            "type": "string",
            "format": "date"
          },
          "isComplete": {
            "type": "boolean"
          }
        },
        "additionalProperties": false
      },
      "DeviceRequestsDTO": {
        "type": "object",
        "properties": {
          "categoryID": {
            "type": "string",
            "format": "uuid"
          },
          "deviceName": {
            "type": "string",
            "nullable": true
          },
          "deviceCount": {
            "type": "integer",
            "format": "int32"
          },
          "officeId": {
            "type": "string",
            "format": "uuid"
          },
          "date": {
            "type": "string",
            "format": "date"
          }
        },
        "additionalProperties": false
      },
      "DeviceTransferDTO": {
        "type": "object",
        "properties": {
          "oldEmpId": {
            "type": "string",
            "format": "uuid"
          },
          "newEmpId": {
            "type": "string",
            "format": "uuid"
          },
          "deviceID": {
            "type": "string",
            "format": "uuid"
          },
          "dateOnly": {
            "type": "string",
            "format": "date"
          }
        },
        "additionalProperties": false
      },
      "EmployeeDTO": {
        "type": "object",
        "properties": {
          "id": {
            "type": "string",
            "format": "uuid"
          },
          "name": {
            "type": "string",
            "nullable": true
          },
          "position": {
            "type": "string",
            "nullable": true
          },
          "email": {
            "type": "string",
            "nullable": true
          }
        },
        "additionalProperties": false
      },
      "EmployeeDeviceAssignmentDTO": {
        "type": "object",
        "properties": {
          "deviceID": {
            "type": "string",
            "format": "uuid"
          },
          "employeeID": {
            "type": "string",
            "format": "uuid"
          },
          "assignDate": {
            "type": "string",
            "format": "date"
          },
          "deviceStatus": {
            "type": "string",
            "nullable": true
          },
          "qty": {
            "type": "integer",
            "format": "int32"
          }
        },
        "additionalProperties": false
      },
      "EmployeeDeviceReturn": {
        "type": "object",
        "properties": {
          "id": {
            "type": "string",
            "format": "uuid"
          },
          "deviceID": {
            "type": "string",
            "format": "uuid"
          },
          "returnDate": {
            "type": "string",
            "format": "date"
          },
          "returnStatus": {
            "type": "string",
            "nullable": true
          }
        },
        "additionalProperties": false
      },
      "LoginDto": {
        "type": "object",
        "properties": {
          "email": {
            "type": "string",
            "nullable": true
          },
          "password": {
            "type": "string",
            "nullable": true
          }
        },
        "additionalProperties": false
      },
      "OfficeDTO": {
        "type": "object",
        "properties": {
          "id": {
            "type": "string",
            "format": "uuid"
          },
          "name": {
            "type": "string",
            "nullable": true
          }
        },
        "additionalProperties": false
      },
      "OfficeDeviceAssignmentDTO": {
        "type": "object",
        "properties": {
          "deviceID": {
            "type": "string",
            "format": "uuid"
          },
          "officeID": {
            "type": "string",
            "format": "uuid"
          },
          "assignDate": {
            "type": "string",
            "format": "date"
          },
          "deviceStatus": {
            "type": "string",
            "nullable": true
          },
          "qty": {
            "type": "integer",
            "format": "int32"
          }
        },
        "additionalProperties": false
      },
      "OfficeDeviceReturnDTO": {
        "type": "object",
        "properties": {
          "id": {
            "type": "string",
            "format": "uuid"
          },
          "devAss": {
            "type": "string",
            "format": "uuid"
          },
          "returnDate": {
            "type": "string",
            "format": "date"
          },
          "returnStatus": {
            "type": "string",
            "nullable": true
          }
        },
        "additionalProperties": false
      },
      "RegisterUserDto": {
        "type": "object",
        "properties": {
          "fullName": {
            "type": "string",
            "nullable": true
          },
          "email": {
            "type": "string",
            "nullable": true
          },
          "password": {
            "type": "string",
            "nullable": true
          },
          "role": {
            "type": "string",
            "nullable": true
          }
        },
        "additionalProperties": false
      },
      "SupplierDTO": {
        "type": "object",
        "properties": {
          "id": {
            "type": "string",
            "format": "uuid"
          },
          "name": {
            "type": "string",
            "nullable": true
          },
          "phoneNumber": {
            "type": "string",
            "nullable": true
          }
        },
        "additionalProperties": false
      }
    }
  }
}